solid_client_credentials/__init__.py
solid_client_credentials/__main__.py
solid_client_credentials/access_token.py
solid_client_credentials/dpop_token_provider.py
solid_client_credentials/dpop_utils.py
solid_client_credentials/openid_config.py
solid_client_credentials/solid_client_credentials_auth.py
solid_client_credentials/tests/__init__.py
solid_client_credentials/tests/conftest.py
solid_client_credentials/tests/test_dpop_utils.py
solidclientcredentials-1.0.3.dist-info/LICENSE.md
solidclientcredentials-1.0.3.dist-info/METADATA
solidclientcredentials-1.0.3.dist-info/WHEEL
solidclientcredentials-1.0.3.dist-info/RECORD
