Metadata-Version: 2.3
Name: SolidClientCredentials
Version: 1.0.3
Summary: Solid authentication with client credentials
License: MIT
Author: A_A
Author-email: 21040751+Otto-AA@users.noreply.github.com
Requires-Python: >=3.10,<4.0
Classifier: Development Status :: 5 - Production/Stable
Classifier: License :: OSI Approved :: MIT License
Classifier: Natural Language :: English
Classifier: Operating System :: OS Independent
Classifier: Programming Language :: Python
Classifier: Programming Language :: Python :: 3
Classifier: Programming Language :: Python :: 3.10
Classifier: Programming Language :: Python :: 3.11
Classifier: Programming Language :: Python :: 3.12
Classifier: Programming Language :: Python :: 3.13
Requires-Dist: jwcrypto (>=1.4.2,<2.0.0)
Requires-Dist: pyjwt (>=2.6.0,<3.0.0)
Requires-Dist: types-requests (>=2.28.11.13,<3.0.0.0)
Project-URL: Documentation, https://SolidClientCredentials.readthedocs.io
Project-URL: Homepage, https://pypi.org/project/SolidClientCredentials
Project-URL: Repository, https://github.com/Otto-AA/solid-client-credentials-py
